bob/__init__.py
bob/cli.py
bob/models.py
bob/utils.py
bob_builder-0.0.20.dist-info/METADATA
bob_builder-0.0.20.dist-info/WHEEL
bob_builder-0.0.20.dist-info/entry_points.txt
bob_builder-0.0.20.dist-info/top_level.txt
bob_builder-0.0.20.dist-info/RECORD
