Metadata-Version: 2.1
Name: bob-builder
Version: 0.0.20
Summary: Binary Build Toolkit.
Home-page: https://github.com/heroku-python/bob-builder
Author: Heroku
Author-email: cfaist@heroku.com
License: MIT
Requires-Dist: boto3
Requires-Dist: docopt
Requires-Dist: natsort
